setup.cfg
setup.py
filcutils/__init__.py
filcutils/configs.py
filcutils/dicts.py
filcutils/version.py
filcutils.egg-info/PKG-INFO
filcutils.egg-info/SOURCES.txt
filcutils.egg-info/dependency_links.txt
filcutils.egg-info/not-zip-safe
filcutils.egg-info/top_level.txt