Metadata-Version: 1.1
Name: filcutils
Version: 0.1.0
Summary: Filc's util function collection...
Home-page: https://github.com/filc/python-filc-utils/
Author: Ujvári Péter
Author-email: peter.ujvari.3@gmail.com
License: Apache2.0
Download-URL: https://github.com/filc/python-filc-utils/tarball/0.1.0
Platform: any
Classifier: Development Status :: 4 - Beta
Classifier: Environment :: Web Environment
Classifier: Intended Audience :: Developers
Classifier: License :: OSI Approved :: BSD License
Classifier: Operating System :: OS Independent
Classifier: Programming Language :: Python :: 3
Classifier: Topic :: Software Development :: Libraries :: Python Modules
